standingsrequests/__init__.py
standingsrequests/admin.py
standingsrequests/app_settings.py
standingsrequests/apps.py
standingsrequests/auth_hooks.py
standingsrequests/constants.py
standingsrequests/decorators.py
standingsrequests/managers.py
standingsrequests/models.py
standingsrequests/providers.py
standingsrequests/tasks.py
standingsrequests/urls.py
standingsrequests/core/__init__.py
standingsrequests/core/app_config.py
standingsrequests/core/contact_types.py
standingsrequests/helpers/__init__.py
standingsrequests/helpers/evecharacter.py
standingsrequests/helpers/evecorporation.py
standingsrequests/helpers/models.py
standingsrequests/helpers/writers.py
standingsrequests/locale/django.pot
standingsrequests/locale/de/LC_MESSAGES/django.po
standingsrequests/locale/en/LC_MESSAGES/django.po
standingsrequests/locale/es/LC_MESSAGES/django.po
standingsrequests/locale/fr_FR/LC_MESSAGES/django.po
standingsrequests/locale/it_IT/LC_MESSAGES/django.po
standingsrequests/locale/ja/LC_MESSAGES/django.po
standingsrequests/locale/ko/LC_MESSAGES/django.po
standingsrequests/locale/ko_KR/LC_MESSAGES/django.po
standingsrequests/locale/ru/LC_MESSAGES/django.po
standingsrequests/locale/uk/LC_MESSAGES/django.po
standingsrequests/locale/zh_Hans/LC_MESSAGES/django.po
standingsrequests/management/commands/standingsrequests_sync_blue_alts.py
standingsrequests/migrations/0001_initial.py
standingsrequests/migrations/0002_contactlabel_labelid_bigintegerfield.py
standingsrequests/migrations/0003_rename_non_pep.py
standingsrequests/migrations/0004_fix_types_and_indices.py
standingsrequests/migrations/0005_refactor_model_names.py
standingsrequests/migrations/0006_add_user_to_revocations.py
standingsrequests/migrations/0007_big_performance_overhaul.py
standingsrequests/migrations/0008_add_revocation_reason.py
standingsrequests/migrations/0009_make_ceo_optional.py
standingsrequests/migrations/0010_add_request_log.py
standingsrequests/migrations/__init__.py
aa_standingsrequests-1.4.1.dist-info/licenses/LICENSE
aa_standingsrequests-1.4.1.dist-info/WHEEL
aa_standingsrequests-1.4.1.dist-info/METADATA
aa_standingsrequests-1.4.1.dist-info/RECORD
