Metadata-Version: 2.4
Name: aa-standingsrequests
Version: 1.4.1
Summary: App for managing character standing requests, made for Alliance Auth.
Author: Basraah
Author-email: Erik Kalkoken <kaloken87@gmail.com>
Requires-Python: >=3.8
Classifier: Environment :: Web Environment
Classifier: Framework :: Django
Classifier: Framework :: Django :: 4.0
Classifier: Framework :: Django :: 4.2
Classifier: Intended Audience :: End Users/Desktop
Classifier: License :: OSI Approved :: GNU General Public License v3 (GPLv3)
Classifier: Operating System :: OS Independent
Classifier: Programming Language :: Python
Classifier: Programming Language :: Python :: 3.8
Classifier: Programming Language :: Python :: 3.9
Classifier: Programming Language :: Python :: 3.10
Classifier: Programming Language :: Python :: 3.11
Classifier: Topic :: Internet :: WWW/HTTP
Classifier: Topic :: Internet :: WWW/HTTP :: Dynamic Content
License-File: LICENSE
Requires-Dist: allianceauth>=3
Requires-Dist: allianceauth-app-utils>=1.18
Requires-Dist: django-eveuniverse>=0.19.1
Project-URL: Changelog, https://gitlab.com/ErikKalkoken/aa-standingsrequests/-/blob/master/CHANGELOG.md
Project-URL: Homepage, https://gitlab.com/ErikKalkoken/aa-standingsrequests
Project-URL: Source, https://gitlab.com/ErikKalkoken/aa-standingsrequests
Project-URL: Tracker, https://gitlab.com/ErikKalkoken/aa-standingsrequests/-/issues
